libranet_logging/__init__.py
libranet_logging/_version.py
libranet_logging/filters.py
libranet_logging/logconfig.py
libranet_logging/loglevel.py
libranet_logging/py.typed
libranet_logging/utils.py
libranet_logging/validate.py
libranet_logging/yaml.py
libranet_logging/etc/logging.yaml
libranet_logging-1.5.2.dist-info/METADATA
libranet_logging-1.5.2.dist-info/WHEEL
libranet_logging-1.5.2.dist-info/RECORD
