Metadata-Version: 2.4
Name: libranet-logging
Version: 1.5.2
Summary: Easy-to-use logging-configuration using a logging.yml-file
Project-URL: Docs, https://libranet-logging.readthedocs.io/en/latest/
Project-URL: Pypi, https://pypi.org/project/libranet-logging
Project-URL: Repo, https://github.com/libranet/libranet-logging
Project-URL: Issues, https://github.com/libranet/libranet-logging/issues
Project-URL: Changelog, https://github.com/libranet/libranet-logging/blob/main/docs/changes.rst
Author-email: Wouter Vanden Hove <wouter@libranet.eu>
Maintainer-email: Wouter Vanden Hove <wouter@libranet.eu>
License: # MIT License
Keywords: filters,handlers,libranet,loggers,logging,yaml
Classifier: Development Status :: 4 - Beta
Classifier: Environment :: Console
Classifier: Intended Audience :: Developers
Classifier: License :: OSI Approved :: MIT License
Classifier: Natural Language :: English
Classifier: Operating System :: POSIX
Classifier: Operating System :: POSIX :: Linux
Classifier: Programming Language :: Python :: 3.8
Classifier: Programming Language :: Python :: 3.9
Classifier: Programming Language :: Python :: 3.10
Classifier: Programming Language :: Python :: 3.11
Classifier: Programming Language :: Python :: 3.12
Classifier: Programming Language :: Python :: 3.13
Classifier: Programming Language :: Python :: Implementation :: CPython
Classifier: Programming Language :: Python :: Implementation :: PyPy
Classifier: Topic :: Software Development :: Libraries
Classifier: Typing :: Typed
Requires-Python: >=3.8
Requires-Dist: colorlog>=6.7
Requires-Dist: importlib-metadata<8,>=7.1.0; python_version < '3.10'
Requires-Dist: importlib-resources>=6.4.5; python_full_version < '3.11'
Requires-Dist: jsonschema>=4.23
Requires-Dist: logging-tree>=1.9
Requires-Dist: pyyaml>=6.0
